{ 
 "Afghanistan" : "Afghan",
 "Åland Islands (AX1)" : "of the Åland Islands",
 "Albania" : "Albanian",
 "Algeria" : "Algerian",
 "American Samoa (AS1)" : "American Samoan",
 "Andorra" : "Andorran",
 "Angola" : "Angolan",
 "Anguilla (AI1)" : "Anguillan",
 "Antarctica" : "Antarctic",
 "Antigua and Barbuda" : "of Antigua and Barbuda",
 "Argentina" : "Argentine; Argentinian",
 "Armenia" : "Armenian",
 "Aruba (AW1)" : "Aruban",
 "Australia" : "Australian",
 "Austria" : "Austrian",
 "Azerbaijan" : "Azerbaijani",
 "Bahamas" : "Bahamian",
 "Bahrain" : "Bahraini",
 "Bangladesh" : "Bangladeshi",
 "Barbados" : "Barbadian",
 "Belarus" : "Belarusian",
 "Belgium" : "Belgian",
 "Belize" : "Belizean",
 "Benin" : "Beninese",
 "Bermuda (BM1)" : "Bermudian",
 "Bhutan" : "Bhutanese",
 "Bolivia" : "Bolivian",
 "Bosnia and Herzegovina" : "of Bosnia and Herzegovina",
 "Botswana" : "Botswanan",
 "Bouvet Island (BV1)" : "of Bouvet Island",
 "Brazil" : "Brazilian",
 "British Indian Ocean Territory (IO1)" : "of the British Indian Ocean Territory",
 "British Virgin Islands (VG1)" : "of the British Virgin Islands",
 "Brunei" : "Bruneian",
 "Bulgaria" : "Bulgarian",
 "Burkina Faso" : "Burkinabe",
 "Burundi" : "Burundian",
 "Cambodia" : "Cambodian",
 "Cameroon" : "Cameroonian",
 "Canada" : "Canadian",
 "Cape Verde" : "Cape Verdean",
 "Cayman Islands (KY1)" : "Caymanian",
 "Central African Republic" : "Central African",
 "Chad" : "Chadian",
 "Chile" : "Chilean",
 "China" : "Chinese",
 "Christmas Island (CX1)" : "of Christmas Island",
 "Clipperton (CP1)" : "of Clipperton Island",
 "Cocos (Keeling) Islands (CC1)" : "of the Cocos (Keeling) Islands",
 "Colombia" : "Colombian",
 "Comoros" : "Comorian",
 "Congo (CG*)" : "Congolese",
 "Cook Islands (CK1)" : "of the Cook Islands",
 "Costa Rica" : "Costa Rican",
 "Côte d’Ivoire" : "Ivorian",
 "Croatia" : "Croatian",
 "Cuba" : "Cuban",
 "Curaçao (CW1)" : "of Curaçao",
 "Cyprus" : "Cypriot",
 "Czech Republic" : "Czech",
 "Democratic Republic of the Congo (CD*)" : "of the Democratic Republic of the Congo (CD1)",
 "Denmark" : "Danish",
 "Djibouti" : "of Djibouti",
 "Dominica" : "of Dominica",
 "Dominican Republic" : "Dominican",
 "Ecuador" : "Ecuadorian",
 "Egypt" : "Egyptian",
 "El Salvador" : "Salvadorian; Salvadoran",
 "Equatorial Guinea" : "of Equatorial Guinea",
 "Eritrea" : "Eritrean",
 "Estonia" : "Estonian",
 "Ethiopia" : "Ethiopian",
 "Faeroe Islands (FO1)" : "Faeroese",
 "Falkland Islands (FK1)" : "of the Falkland Islands",
 "Fiji" : "Fijian",
 "Finland" : "Finnish",
 "former Yugoslav Republic of Macedonia, the (5a)" : "of the former Yugoslav Republic of Macedonia",
 "France" : "French",
 "French Guiana (GF1)" : "Guianese",
 "French Polynesia (PF1)" : "Polynesian",
 "French Southern and Antarctic Lands (TF1)" : "of the French Southern and Antarctic Lands",
 "Gabon" : "Gabonese",
 "Georgia" : "Georgian",
 "Germany" : "German",
 "Ghana" : "Ghanaian",
 "Gibraltar (GI1)" : "Gibraltarian",
 "Greece" : "Greek",
 "Greenland (GL1)" : "Greenlandic",
 "Grenada" : "Grenadian",
 "Guadeloupe (GP1)" : "Guadeloupean",
 "Guam (GU1)" : "Guamanian",
 "Guatemala" : "Guatemalan",
 "Guernsey (GG1)" : "Guernsey",
 "Guinea" : "Guinean",
 "Guinea-Bissau" : "of Guinea-Bissau",
 "Guyana" : "Guyanese",
 "Haiti" : "Haitian",
 "Heard Island and McDonald Islands (HM1)" : "of the Heard Island and McDonald Islands",
 "the Holy See/Vatican City State (VA1)" : "of the Holy See/of the Vatican",
 "Honduras" : "Honduran",
 "Hong Kong (HK1)" : "Hong Kong Chinese",
 "Hungary" : "Hungarian",
 "Iceland" : "Icelandic",
 "India" : "Indian",
 "Indonesia" : "Indonesian",
 "Iran" : "Iranian",
 "Iraq" : "Iraqi",
 "Ireland" : "Irish",
 "Isle of Man (IM1)" : "Manx",
 "Israel" : "Israeli",
 "Italy" : "Italian",
 "Jamaica" : "Jamaican",
 "Japan" : "Japanese",
 "Jersey (JE1)" : "Jersey",
 "Jordan" : "Jordanian",
 "Kazakhstan" : "Kazakh",
 "Kenya" : "Kenyan",
 "Kiribati" : "Kiribatian",
 "Kuwait" : "Kuwaiti",
 "Kyrgyzstan" : "Kyrgyz",
 "Laos" : "Lao; Laotian",
 "Latvia" : "Latvian",
 "Lebanon" : "Lebanese",
 "Lesotho" : "of Lesotho",
 "Liberia" : "Liberian",
 "Libya" : "Libyan",
 "Liechtenstein" : "of Liechtenstein",
 "Lithuania" : "Lithuanian",
 "Luxembourg" : "Luxembourgish",
 "Macao (MO1)" : "Macanese",
 "Madagascar" : "Malagasy",
 "Malawi" : "Malawian",
 "Malaysia" : "Malaysian",
 "Maldives" : "Maldivian",
 "Mali" : "Malian",
 "Malta" : "Maltese",
 "Marshall Islands" : "Marshallese",
 "Martinique (MQ1)" : "Martinican",
 "Mauritania" : "Mauritanian",
 "Mauritius" : "Mauritian",
 "Mayotte (YT1)" : "Mahoran",
 "Mexico" : "Mexican",
 "Micronesia" : "of Micronesia",
 "Moldova" : "Moldovan",
 "Monaco" : "Monegasque",
 "Mongolia" : "Mongolian",
 "Montenegro" : "Montenegrin",
 "Montserrat (MS1)" : "Montserratian",
 "Morocco" : "Moroccan",
 "Mozambique" : "Mozambican",
 "Myanmar/Burma" : "of Myanmar/Burma ",
 "Namibia" : "Namibian",
 "Nauru" : "Nauruan",
 "Nepal" : "Nepalese",
 "Netherlands (NL1)" : "Netherlands; Dutch",
 "New Caledonia (NC1)" : "New Caledonian",
 "New Zealand" : "of New Zealand",
 "Nicaragua" : "Nicaraguan",
 "Niger" : "Nigerien",
 "Nigeria" : "Nigerian",
 "Niue (NU1)" : "Niuean",
 "Norfolk Island (NF1)" : "of Norfolk Island",
 "North Korea" : "North Korean",
 "Northern Mariana Islands (MP1)" : "of the Northern Mariana Islands",
 "Norway" : "Norwegian",
 "Oman" : "Omani",
 "Pakistan" : "Pakistani",
 "Palau" : "Palauan",
 "Panama" : "Panamanian",
 "Papua New Guinea" : "of Papua New Guinea",
 "Paraguay" : "Paraguayan",
 "Peru" : "Peruvian",
 "Philippines" : "Philippine",
 "Pitcairn Islands (PN1)" : "Pitcairner",
 "Poland" : "Polish",
 "Portugal" : "Portuguese",
 "Puerto Rico (PR1)" : "Puerto Rican",
 "Qatar" : "Qatari",
 "Réunion (RE1)" : "Reunionese",
 "Romania" : "Romanian",
 "Russia" : "Russian",
 "Rwanda" : "Rwandan; Rwandese",
 "Saint Barthélemy (BL1)" : "of Saint Barthélemy",
 "Saint Helena, Ascension and Tristan da Cunha  (SH1)" : "of Saint Helena, Ascension and Tristan da Cunha",
 "Saint Kitts and Nevis" : "of Saint Kitts and Nevis",
 "Saint Lucia" : "Saint Lucian",
 "Saint Martin (MF1)" : "of Saint Martin",
 "Saint Pierre and Miquelon (PM1)" : "of Saint Pierre and Miquelon",
 "Saint Vincent and the Grenadines" : "Vincentian; of Saint Vincent and the Grenadines",
 "Samoa" : "Samoan",
 "San Marino" : "of San Marino",
 "São Tomé and Príncipe" : "of São Tomé and Príncipe",
 "Saudi Arabia" : "Saudi Arabian",
 "Senegal" : "Senegalese",
 "Serbia" : "Serbian",
 "Seychelles" : "of Seychelles",
 "Sierra Leone" : "Sierra Leonean",
 "Singapore" : "Singaporean",
 "Sint Maarten (SX1)" : "of Sint Maarten",
 "Slovakia" : "Slovak; Slovakian",
 "Slovenia" : "Slovenian",
 "Solomon Islands" : "of the Solomon Islands",
 "Somalia" : "Somali; Somalian",
 "South Africa" : "South African",
 "South Georgia and the South Sandwich Islands (GS1)" : "of South Georgia and the South Sandwich Islands",
 "South Korea" : "South Korean",
 "South Sudan" : "South Sudanese",
 "Spain" : "Spanish",
 "Sri Lanka" : "Sri Lankan",
 "Sudan" : "Sudanese",
 "Suriname" : "Surinamese",
 "Svalbard and Jan Mayen (SJ1)" : "of Svalbard, of Jan Mayen",
 "Swaziland" : "Swazi",
 "Sweden" : "Swedish",
 "Switzerland" : "Swiss",
 "Syria" : "Syrian",
 "Taiwan" : "Taiwanese",
 "Tajikistan" : "Tajik",
 "Tanzania" : "Tanzanian",
 "Thailand" : "Thai",
 "The Gambia (GM*)" : "Gambian",
 "Timor-Leste" : "East Timorese",
 "Togo" : "Togolese",
 "Tokelau (TK1)" : "Tokelauan",
 "Tonga" : "Tongan",
 "Trinidad and Tobago" : "of Trinidad and Tobago",
 "Tunisia" : "Tunisian",
 "Turkey" : "Turkish",
 "Turkmenistan" : "Turkmen",
 "Turks and Caicos Islands (TC1)" : "of the Turks and Caicos Islands",
 "Tuvalu" : "Tuvaluan",
 "Uganda" : "Ugandan",
 "Ukraine" : "Ukrainian",
 "United Arab Emirates" : "Emirian",
 "United Kingdom" : "British",
 "United States" : "American; of the United States",
 "United States Minor Outlying Islands (UM1)" : "—",
 "Uruguay" : "Uruguayan",
 "US Virgin Islands (VI1)" : "of the US Virgin Islands",
 "Uzbekistan" : "Uzbek",
 "Vanuatu" : "Vanuatuan",
 "Venezuela" : "Venezuelan",
 "Vietnam" : "Vietnamese",
 "Wallis and Futuna (WF1)" : "of the Wallis and Futuna Islands",
 "Western Sahara (EH1)" : "Sahrawi",
 "Yemen" : "Yemeni",
 "Zambia" : "Zambian",
 "Zimbabwe" : "Zimbabwean"
}
